uniqmin/__init__.py
uniqmin/__main__.py
uniqmin-1.3.0.dist-info/METADATA
uniqmin-1.3.0.dist-info/WHEEL
uniqmin-1.3.0.dist-info/entry_points.txt
uniqmin-1.3.0.dist-info/top_level.txt
uniqmin-1.3.0.dist-info/RECORD
