Metadata-Version: 2.1
Name: uniqmin
Version: 1.3.0
Summary: An alignment-independent tool for the study of pathogen sequence diversity at any given rank of taxonomy lineage
Home-page: UNKNOWN
Author: Chong LC
Author-email: <lichuinchong@gmail.com>
License: UNKNOWN
Project-URL: Github, https://github.com/ChongLC/MinimalSetofViralPeptidome-UNIQmin
Keywords: virus,pathogen,sequence diversity,alignment-independent,minimal set,proteome
Platform: UNKNOWN
Classifier: Development Status :: 5 - Production/Stable
Classifier: Intended Audience :: Science/Research
Classifier: Intended Audience :: Education
Classifier: Programming Language :: Python :: 3
Classifier: Programming Language :: Python :: 3.7
Classifier: Programming Language :: Python :: 3.8
Classifier: Programming Language :: Python :: 3.9
Classifier: Programming Language :: Python :: 3.10
Classifier: Programming Language :: Python :: 3.11
Classifier: Operating System :: Unix
Classifier: License :: OSI Approved :: MIT License
Classifier: Natural Language :: English
Classifier: Topic :: Scientific/Engineering :: Bio-Informatics
Requires-Dist: biopython (==1.79)
Requires-Dist: pandas (>=1.3.5)
Requires-Dist: pyahocorasick (==1.4.1)
